mcreweight-0.2.8.dist-info/licenses/LICENSE
mult_and_kin_reweight/__init__.py
mult_and_kin_reweight/config.py
mult_and_kin_reweight/core.py
mult_and_kin_reweight/io.py
mult_and_kin_reweight/train.py
scripts/__init__.py
scripts/apply_weights.py
scripts/run_reweighting.py
utils/__init__.py
utils/plotting_utils.py
utils/utils.py
mcreweight-0.2.8.dist-info/METADATA
mcreweight-0.2.8.dist-info/WHEEL
mcreweight-0.2.8.dist-info/entry_points.txt
mcreweight-0.2.8.dist-info/top_level.txt
mcreweight-0.2.8.dist-info/RECORD
