Metadata-Version: 2.4
Name: mcreweight
Version: 0.2.8
Summary: A package for reweighting MC samples to match data
Author-email: Tommaso Fulghesu <tommaso.fulghesu@cern.ch>
License: GNU GENERAL PUBLIC LICENSE
Requires-Python: >=3.8
License-File: LICENSE
Requires-Dist: numpy>=1.20.0
Requires-Dist: pandas>=1.3.0
Requires-Dist: matplotlib>=3.4.0
Requires-Dist: scikit-learn>=1.0.0
Requires-Dist: optuna>=2.10.0
Requires-Dist: hep_ml>=0.7.0
Requires-Dist: seaborn>=0.11.0
Requires-Dist: awkward-pandas>=2023.8.0
Requires-Dist: numexpr>=2.7.0
Requires-Dist: uproot>=5.0.0
Requires-Dist: awkward>=2.6.0
Dynamic: license-file
